{
  "name": "Process",
  "fields": [
    {
      "fieldName": "processName",
      "fieldType": "String",
      "fieldValidateRules": [
        "required"
      ]
    },
    {
      "fieldName": "descProcess",
      "fieldType": "String"
    }
  ],
  "relationships": [
    {
      "relationshipType": "one-to-many",
      "otherEntityName": "action",
      "otherEntityRelationshipName": "process",
      "relationshipName": "actions"
    },
    {
      "relationshipType": "many-to-one",
      "otherEntityName": "application",
      "otherEntityRelationshipName": "processes",
      "relationshipName": "application",
      "otherEntityField": "appName"
    },
    {
      "relationshipType": "many-to-one",
      "otherEntityName": "server",
      "otherEntityRelationshipName": "processes",
      "relationshipName": "server",
      "otherEntityField": "serverName"
    }
  ],
  "changelogDate": "20200820211604",
  "entityTableName": "process",
  "dto": "no",
  "pagination": "pagination",
  "service": "serviceImpl",
  "jpaMetamodelFiltering": false,
  "fluentMethods": true,
  "readOnly": false,
  "embedded": false,
  "clientRootFolder": "",
  "applications": "*"
}
